printListModule.py
setup.py
printListModule.egg-info/PKG-INFO
printListModule.egg-info/SOURCES.txt
printListModule.egg-info/dependency_links.txt
printListModule.egg-info/top_level.txt