Metadata-Version: 1.0
Name: printListModule
Version: 1.0.0
Summary: An API to print list recursively
Home-page: UNKNOWN
Author: Maulik
Author-email: maulik.jodhani@ignitarium.com
License: UNKNOWN
Platform: UNKNOWN
